llama_index/postprocessor/aimon_rerank/__init__.py
llama_index/postprocessor/aimon_rerank/base.py
llama_index_postprocessor_aimon_rerank-0.2.1.dist-info/METADATA
llama_index_postprocessor_aimon_rerank-0.2.1.dist-info/WHEEL
llama_index_postprocessor_aimon_rerank-0.2.1.dist-info/licenses/LICENSE
llama_index_postprocessor_aimon_rerank-0.2.1.dist-info/RECORD
