Metadata-Version: 2.4
Name: llama-index-postprocessor-aimon-rerank
Version: 0.2.1
Summary: llama-index postprocessor aimon rerank integration
Author-email: AIMon <info@aimon.ai>
License-Expression: MIT
License-File: LICENSE
Requires-Python: <4.0,>=3.9
Requires-Dist: aimon
Requires-Dist: llama-index-core<0.15,>=0.13.0
